{
    "_id":  "aggressive_portfolio_ability_id",
    "category":  "abilities",
    "description":  "If it survives the wave, it gains $1 mana based on the wave number and earns |img(icons/Gold.png) $2 per mana. If it dies, it loses ALL mana.",
    "descriptionId":  "aggressive_portfolio_description",
    "iconPath":  "Icons/AggressivePortfolio.png",
    "name":  "Aggressive Portfolio",
    "tooltip":  "If it survives the wave, it gains 1-6 mana based on the wave number and earns \u0026lt;img class=\u0027tooltip-icon\u0027 src=\u0027hud/img/icons/Gold.png\u0027 /\u0026gt; 3 per mana. If it dies, it loses ALL mana."
}
